dictionary/__init__.py
dictionary/dictionary.py
brkyldrn_dictionary_cs453-2.0.0.dist-info/METADATA
brkyldrn_dictionary_cs453-2.0.0.dist-info/WHEEL
brkyldrn_dictionary_cs453-2.0.0.dist-info/top_level.txt
brkyldrn_dictionary_cs453-2.0.0.dist-info/RECORD
