Metadata-Version: 2.1
Name: brkyldrn-dictionary-cs453
Version: 2.0.0
Summary: UNKNOWN
Author: Ömer Burak Yıldıran
License: UNKNOWN
Platform: UNKNOWN
Requires-Python: >=3.8
Requires-Dist: requests (>=2.23.0)
